ptfp/__init__.py
ptfp/_version.py
ptfp/bilby_pipe_interface.py
ptfp/configuration.py
ptfp/frequency_domain_plots.py
ptfp/patches.py
ptfp/spectrograms.py
ptfp/time_domain_plots.py
ptfp/time_frequency_tracks.py
ptfp/waveform_generators.py
ptfp/waveforms.py
ptfp-0.2.2.dist-info/LICENSE.md
ptfp-0.2.2.dist-info/METADATA
ptfp-0.2.2.dist-info/WHEEL
ptfp-0.2.2.dist-info/top_level.txt
ptfp-0.2.2.dist-info/RECORD
