Metadata-Version: 2.2
Name: ptfp
Version: 0.2.2
Summary: Random tools to assist in making pretty plots for PE, especially with bilby.
Author-email: Rhiannon Udall <rhiannon.udall@ligo.org>
Project-URL: Homepage, https://github.com/Rhiannon-Udall/RhiannonsUtils
Project-URL: Bug Tracker, https://github.com/Rhiannon-Udall/RhiannonsUtils/-/issues
Classifier: Programming Language :: Python :: 3
Classifier: License :: OSI Approved :: MIT License
Classifier: Operating System :: OS Independent
Requires-Python: >=3.8
License-File: LICENSE.md
Requires-Dist: bilby[gw]
Requires-Dist: bilby_pipe
Requires-Dist: pycbc
